ColorScript/__init__.py
ColorScript/data.py
ColorScript/functions.py
ColorScript-2024.2.3.dist-info/LICENSE
ColorScript-2024.2.3.dist-info/METADATA
ColorScript-2024.2.3.dist-info/WHEEL
ColorScript-2024.2.3.dist-info/top_level.txt
ColorScript-2024.2.3.dist-info/RECORD
