Metadata-Version: 2.1
Name: ColorScript
Version: 2024.2.3
Summary: A package for functionality with text, escape codes, octal and hexadecimal codes, and other data.
Author-email: Tariq Tayebi <tariq.tayebi1@education.nsw.gov.au>
Project-URL: Homepage, https://github.com/TariqTheCoder/ColourScript-Documentation/
Project-URL: Documentation, https://colourscript-documentation.readthedocs.io/
Project-URL: Issues, https://github.com/TariqTheCoder/ColourScript-Documentation/issues/1
Classifier: Programming Language :: Python :: 3
Classifier: License :: OSI Approved :: MIT License
Classifier: Operating System :: OS Independent
Requires-Python: >=2.0
License-File: LICENSE
